{
  "type": "Feature",
  "properties": {
    "gn:admin1_code":"110",
    "gn:asciiname":"As Perdido Hamlet",
    "gn:country_code":"MP",
    "gn:dem":30,
    "gn:elevation":"40.0",
    "gn:feature_class":"P",
    "gn:feature_code":"PPL",
    "gn:name":"As Perdido Hamlet",
    "gn:population":0,
    "gn:timezone":"Pacific/Saipan",
    "iso:country":"MP",
    "wof:name":"As Perdido Hamlet",
    "wof:placetype":"locality"
},
  "geometry": {"coordinates":[145.70920000000001,15.1339],"type":"Point"}
}