{
  "type": "Feature",
  "properties": {
    "gn:admin1_code":"110",
    "gn:asciiname":"Garapan Village",
    "gn:country_code":"MP",
    "gn:dem":7,
    "gn:elevation":"6.0",
    "gn:feature_class":"P",
    "gn:feature_code":"PPL",
    "gn:name":"Garapan Village",
    "gn:population":0,
    "gn:timezone":"Pacific/Saipan",
    "iso:country":"MP",
    "name:und_x_variant":[
        "Garapan CDP"
    ],
    "wof:name":"Garapan Village",
    "wof:placetype":"locality"
},
  "geometry": {"coordinates":[145.72024999999999,15.20545],"type":"Point"}
}