{
  "type": "Feature",
  "properties": {
    "gn:admin1_code":"110",
    "gn:asciiname":"Achugao Hamlet",
    "gn:country_code":"MP",
    "gn:dem":186,
    "gn:elevation":"200.0",
    "gn:feature_class":"P",
    "gn:feature_code":"PPL",
    "gn:name":"Achugao Hamlet",
    "gn:population":0,
    "gn:timezone":"Pacific/Saipan",
    "iso:country":"MP",
    "wof:name":"Achugao Hamlet",
    "wof:placetype":"locality"
},
  "geometry": {"coordinates":[145.76706999999999,15.23165],"type":"Point"}
}