{
  "type": "Feature",
  "properties": {
    "iso:country":"MP",
    "name:deu_x_preferred":[
        "Flughafen Saipan"
    ],
    "name:eng_x_preferred":[
        "Saipan International Airport"
    ],
    "name:eng_x_variant":[
        "SPN",
        "PGSN"
    ],
    "name:fas_x_preferred":[
        "\u0641\u0631\u0648\u062f\u06af\u0627\u0647 \u0628\u06cc\u0646\u200c\u0627\u0644\u0645\u0644\u0644\u06cc \u0633\u0627\u06cc\u067e\u0646"
    ],
    "name:fin_x_preferred":[
        "Saipanin kansainv\u00e4linen lentoasema"
    ],
    "name:fra_x_preferred":[
        "Saipan International Airport"
    ],
    "name:ind_x_preferred":[
        "Bandar Udara Internasional Saipan"
    ],
    "name:ita_x_preferred":[
        "Saipan International Airport"
    ],
    "name:jpn_x_preferred":[
        "\u30b5\u30a4\u30d1\u30f3\u56fd\u969b\u7a7a\u6e2f"
    ],
    "name:kor_x_preferred":[
        "\uc0ac\uc774\ud310 \uad6d\uc81c\uacf5\ud56d"
    ],
    "name:nld_x_preferred":[
        "Saipan International Airport"
    ],
    "name:pol_x_preferred":[
        "Port lotniczy Saipan"
    ],
    "name:por_x_preferred":[
        "Saipan International Airport"
    ],
    "name:rus_x_preferred":[
        "\u0421\u0430\u0439\u043f\u0430\u043d"
    ],
    "name:spa_x_preferred":[
        "Aeropuerto Internacional de Saip\u00e1n"
    ],
    "name:swe_x_preferred":[
        "Saipan International Airport"
    ],
    "name:tgk_x_preferred":[
        "\u0424\u0443\u0440\u0443\u0434\u0433\u043e\u04b3\u0438 \u0431\u0438\u043d\u200c\u0430\u043b\u043c\u0438\u043b\u0430\u043b\u04e3 \u0441\u043e\u0438\u043f\u043d"
    ],
    "name:vie_x_preferred":[
        "S\u00e2n bay qu\u1ed1c t\u1ebf Saipan"
    ],
    "name:zho_x_preferred":[
        "\u585e\u73ed\u570b\u969b\u6a5f\u5834"
    ],
    "oa:elevation_ft":"215",
    "oa:type":"medium_airport",
    "wd:wordcount":1484,
    "woe:hierarchy":{
        "country_id":23424788,
        "planet_id":1,
        "state_id":29389658
    },
    "wof:name":"Saipan International Airport",
    "wof:placetype":"campus"
},
  "geometry": {"coordinates":[145.729004,15.119],"type":"Point"}
}