{
  "type": "Feature",
  "properties": {
    "gn:admin1_code":"110",
    "gn:asciiname":"Papago Hamlet",
    "gn:country_code":"MP",
    "gn:dem":209,
    "gn:elevation":"200.0",
    "gn:feature_class":"P",
    "gn:feature_code":"PPL",
    "gn:name":"Papago Hamlet",
    "gn:population":0,
    "gn:timezone":"Pacific/Saipan",
    "iso:country":"MP",
    "wof:name":"Papago Hamlet",
    "wof:placetype":"locality"
},
  "geometry": {"coordinates":[145.74703,15.17358],"type":"Point"}
}