{
  "type": "Feature",
  "properties": {
    "gn:admin1_code":"110",
    "gn:asciiname":"Puerto Rico Village",
    "gn:country_code":"MP",
    "gn:dem":10,
    "gn:elevation":"10.0",
    "gn:feature_class":"P",
    "gn:feature_code":"PPL",
    "gn:name":"Puerto Rico Village",
    "gn:population":0,
    "gn:timezone":"Pacific/Saipan",
    "iso:country":"MP",
    "wof:name":"Puerto Rico Village",
    "wof:placetype":"locality"
},
  "geometry": {"coordinates":[145.73296000000005,15.2197],"type":"Point"}
}