{
  "type": "Feature",
  "properties": {
    "gn:country":"MP",
    "gn:fcode":"HSTS",
    "gn:population":2665,
    "iso:country":"MP",
    "qs:name":"JP Army Garrison WW2",
    "qs:photos_9r":0,
    "qs:photos_sr":0,
    "qs:pop_sr":"4",
    "wof:name":"JP Army Garrison WW2",
    "wof:placetype":"locality",
    "wof:population":2665
},
  "geometry": {"coordinates":[145.20400000000001,14.154],"type":"Point"}
}